README.rst
setup.cfg
setup.py
graph_talk.egg-info/PKG-INFO
graph_talk.egg-info/SOURCES.txt
graph_talk.egg-info/dependency_links.txt
graph_talk.egg-info/top_level.txt
gt/__init__.py
gt/core.py
gt/debug.py
gt/export.py
gt/procs.py
gt/utils.py