Metadata-Version: 1.1
Name: graph-talk
Version: 0.3.1
Summary: Library for structured information processing: parsing, interpreting, converting, etc.
Home-page: https://github.com/krvss/graph-talk/
Author: Stas Kravets
Author-email: stas.kravets@gmail.com
License: Apache Software License
Download-URL: https://github.com/krvss/graph-talk/tarball/0.3
Platform: any
Classifier: Programming Language :: Python
Classifier: Programming Language :: Python :: 2
Classifier: Programming Language :: Python :: 3
Classifier: Development Status :: 4 - Beta
Classifier: Natural Language :: English
Classifier: Environment :: Console
Classifier: Intended Audience :: Developers
Classifier: License :: OSI Approved :: Apache Software License
Classifier: Operating System :: OS Independent
Classifier: Topic :: Software Development :: Libraries :: Python Modules
Classifier: Topic :: Text Processing :: General
